exceptionator/__init__.py
exceptionator/enhancer.py
exceptionator/rendering.py
exceptionator-0.0.1.dist-info/WHEEL
exceptionator-0.0.1.dist-info/LICENSE.txt
exceptionator-0.0.1.dist-info/METADATA
exceptionator-0.0.1.dist-info/RECORD
